LICENSE
MANIFEST.in
README.rst
setup.cfg
setup.py
seq_re/__init__.py
seq_re/seq_re_bootstrap.py
seq_re/seq_re_main.py
seq_re/seq_re_parse.py
seq_re.egg-info/PKG-INFO
seq_re.egg-info/SOURCES.txt
seq_re.egg-info/dependency_links.txt
seq_re.egg-info/top_level.txt