Metadata-Version: 1.1
Name: seq-re
Version: 0.2
Summary: N-dimensional Sequence Regular Expression (SEQ RE)
Home-page: https://github.com/gening/seq_re
Author: GE Ning
Author-email: benjaminzge@gmail.com
License: LGPL-3.0
Keywords: ndarray ndimensional-vector sequences seq regular-expressions regex
Platform: UNKNOWN
Classifier: Development Status :: 3 - Alpha
Classifier: Intended Audience :: Developers
Classifier: Topic :: Text Processing :: General
Classifier: Topic :: Utilities
Classifier: Operating System :: OS Independent
Classifier: License :: OSI Approved :: GNU Lesser General Public License v3 (LGPLv3)
Classifier: Programming Language :: Python :: 2.6
Classifier: Programming Language :: Python :: 2.7
Classifier: Programming Language :: Python :: 3
